setup.py
django_config_url/__init__.py
django_config_url/core.py
django_config_url/flags.py
django_config_url.egg-info/PKG-INFO
django_config_url.egg-info/SOURCES.txt
django_config_url.egg-info/dependency_links.txt
django_config_url.egg-info/top_level.txt