Metadata-Version: 1.0
Name: django-config-url
Version: 0.1.1
Summary: A simple mechanism for loading external configuration from a URL.
Home-page: https://github.com/GannettDigital/django-config-url
Author: Eric Moritz
Author-email: emoritz@gannett.com
License: UNKNOWN
Platform: UNKNOWN
